{"version": "5.2.1", "flags": {}, "shapes": [{"label": "a", "points": [[2331, 2457], [2382, 2504]], "group_id": null, "shape_type": "rectangle", "flags": {}}, {"label": "a", "points": [[2873, 945], [2883, 950]], "group_id": null, "shape_type": "rectangle", "flags": {}}, {"label": "a", "points": [[167, 1100], [173, 1106]], "group_id": null, "shape_type": "rectangle", "flags": {}}, {"label": "a", "points": [[892, 1200], [899, 1206]], "group_id": null, "shape_type": "rectangle", "flags": {}}, {"label": "a", "points": [[181, 1057], [186, 1061]], "group_id": null, "shape_type": "rectangle", "flags": {}}, {"label": "a", "points": [[112, 1742], [119, 1751]], "group_id": null, "shape_type": "rectangle", "flags": {}}, {"label": "a", "points": [[186, 1059], [191, 1064]], "group_id": null, "shape_type": "rectangle", "flags": {}}, {"label": "a", "points": [[2183, 774], [2258, 845]], "group_id": null, "shape_type": "rectangle", "flags": {}}, {"label": "a", "points": [[2205, 599], [2249, 640]], "group_id": null, "shape_type": "rectangle", "flags": {}}, {"label": "a", "points": [[2077, 563], [2108, 591]], "group_id": null, "shape_type": "rectangle", "flags": {}}, {"label": "a", "points": [[2368, 848], [2405, 882]], "group_id": null, "shape_type": "rectangle", "flags": {}}, {"label": "a", "points": [[2422, 910], [2463, 948]], "group_id": null, "shape_type": "rectangle", "flags": {}}, {"label": "a", "points": [[2229, 326], [2302, 394]], "group_id": null, "shape_type": "rectangle", "flags": {}}, {"label": "a", "points": [[2661, 871], [2679, 886]], "group_id": null, "shape_type": "rectangle", "flags": {}}, {"label": "a", "points": [[2657, 916], [2738, 1005]], "group_id": null, "shape_type": "rectangle", "flags": {}}, {"label": "a", "points": [[2711, 712], [2716, 716]], "group_id": null, "shape_type": "rectangle", "flags": {}}, {"label": "a", "points": [[2623, 600], [2631, 607]], "group_id": null, "shape_type": "rectangle", "flags": {}}, {"label": "a", "points": [[772, 1026], [815, 1066]], "group_id": null, "shape_type": "rectangle", "flags": {}}, {"label": "a", "points": [[2227, 278], [2236, 287]], "group_id": null, "shape_type": "rectangle", "flags": {}}, {"label": "a", "points": [[2380, 378], [2386, 384]], "group_id": null, "shape_type": "rectangle", "flags": {}}, {"label": "a", "points": [[2580, 551], [2587, 558]], "group_id": null, "shape_type": "rectangle", "flags": {}}, {"label": "a", "points": [[2179, 647], [2188, 655]], "group_id": null, "shape_type": "rectangle", "flags": {}}, {"label": "a", "points": [[2657, 643], [2662, 646]], "group_id": null, "shape_type": "rectangle", "flags": {}}, {"label": "a", "points": [[2774, 805], [2781, 811]], "group_id": null, "shape_type": "rectangle", "flags": {}}, {"label": "a", "points": [[2699, 693], [2705, 699]], "group_id": null, "shape_type": "rectangle", "flags": {}}, {"label": "a", "points": [[2314, 334], [2321, 341]], "group_id": null, "shape_type": "rectangle", "flags": {}}, {"label": "a", "points": [[2462, 441], [2470, 451]], "group_id": null, "shape_type": "rectangle", "flags": {}}, {"label": "a", "points": [[2662, 646], [2668, 652]], "group_id": null, "shape_type": "rectangle", "flags": {}}, {"label": "a", "points": [[2728, 734], [2732, 738]], "group_id": null, "shape_type": "rectangle", "flags": {}}, {"label": "a", "points": [[2136, 238], [2142, 244]], "group_id": null, "shape_type": "rectangle", "flags": {}}, {"label": "a", "points": [[2224, 160], [2237, 169]], "group_id": null, "shape_type": "rectangle", "flags": {}}, {"label": "a", "points": [[2255, 289], [2266, 304]], "group_id": null, "shape_type": "rectangle", "flags": {}}, {"label": "a", "points": [[136, 1231], [141, 1235]], "group_id": null, "shape_type": "rectangle", "flags": {}}, {"label": "a", "points": [[94, 1534], [100, 1538]], "group_id": null, "shape_type": "rectangle", "flags": {}}, {"label": "a", "points": [[103, 1439], [109, 1444]], "group_id": null, "shape_type": "rectangle", "flags": {}}, {"label": "a", "points": [[110, 1292], [123, 1305]], "group_id": null, "shape_type": "rectangle", "flags": {}}, {"label": "a", "points": [[756, 1376], [800, 1417]], "group_id": null, "shape_type": "rectangle", "flags": {}}, {"label": "a", "points": [[521, 1777], [552, 1805]], "group_id": null, "shape_type": "rectangle", "flags": {}}, {"label": "a", "points": [[250, 1767], [293, 1807]], "group_id": null, "shape_type": "rectangle", "flags": {}}, {"label": "a", "points": [[113, 1342], [119, 1347]], "group_id": null, "shape_type": "rectangle", "flags": {}}, {"label": "a", "points": [[738, 2057], [781, 2096]], "group_id": null, "shape_type": "rectangle", "flags": {}}, {"label": "a", "points": [[841, 1247], [878, 1281]], "group_id": null, "shape_type": "rectangle", "flags": {}}, {"label": "a", "points": [[1014, 1623], [1059, 1665]], "group_id": null, "shape_type": "rectangle", "flags": {}}, {"label": "a", "points": [[631, 2020], [674, 2060]], "group_id": null, "shape_type": "rectangle", "flags": {}}, {"label": "a", "points": [[979, 1827], [1015, 1859]], "group_id": null, "shape_type": "rectangle", "flags": {}}, {"label": "a", "points": [[461, 1902], [492, 1929]], "group_id": null, "shape_type": "rectangle", "flags": {}}, {"label": "a", "points": [[289, 1580], [318, 1608]], "group_id": null, "shape_type": "rectangle", "flags": {}}, {"label": "a", "points": [[295, 1254], [323, 1278]], "group_id": null, "shape_type": "rectangle", "flags": {}}, {"label": "a", "points": [[208, 1455], [258, 1501]], "group_id": null, "shape_type": "rectangle", "flags": {}}, {"label": "a", "points": [[420, 1024], [452, 1053]], "group_id": null, "shape_type": "rectangle", "flags": {}}, {"label": "a", "points": [[920, 1119], [971, 1174]], "group_id": null, "shape_type": "rectangle", "flags": {}}, {"label": "a", "points": [[420, 1510], [473, 1564]], "group_id": null, "shape_type": "rectangle", "flags": {}}, {"label": "a", "points": [[847, 1875], [866, 1891]], "group_id": null, "shape_type": "rectangle", "flags": {}}, {"label": "a", "points": [[289, 1651], [313, 1672]], "group_id": null, "shape_type": "rectangle", "flags": {}}, {"label": "a", "points": [[285, 1616], [313, 1642]], "group_id": null, "shape_type": "rectangle", "flags": {}}, {"label": "a", "points": [[467, 1622], [505, 1656]], "group_id": null, "shape_type": "rectangle", "flags": {}}, {"label": "a", "points": [[851, 1104], [889, 1140]], "group_id": null, "shape_type": "rectangle", "flags": {}}, {"label": "a", "points": [[698, 1749], [727, 1776]], "group_id": null, "shape_type": "rectangle", "flags": {}}, {"label": "a", "points": [[614, 1742], [654, 1779]], "group_id": null, "shape_type": "rectangle", "flags": {}}, {"label": "a", "points": [[360, 1043], [396, 1078]], "group_id": null, "shape_type": "rectangle", "flags": {}}, {"label": "a", "points": [[170, 1225], [200, 1252]], "group_id": null, "shape_type": "rectangle", "flags": {}}, {"label": "a", "points": [[194, 1912], [229, 1947]], "group_id": null, "shape_type": "rectangle", "flags": {}}, {"label": "a", "points": [[325, 1373], [364, 1411]], "group_id": null, "shape_type": "rectangle", "flags": {}}, {"label": "a", "points": [[188, 2007], [205, 2017]], "group_id": null, "shape_type": "rectangle", "flags": {}}, {"label": "a", "points": [[122, 1802], [127, 1806]], "group_id": null, "shape_type": "rectangle", "flags": {}}, {"label": "a", "points": [[2719, 717], [2724, 722]], "group_id": null, "shape_type": "rectangle", "flags": {}}, {"label": "a", "points": [[1622, 892], [1651, 918]], "group_id": null, "shape_type": "rectangle", "flags": {}}, {"label": "a", "points": [[1600, 435], [1636, 468]], "group_id": null, "shape_type": "rectangle", "flags": {}}, {"label": "a", "points": [[1539, 466], [1553, 479]], "group_id": null, "shape_type": "rectangle", "flags": {}}, {"label": "a", "points": [[1212, 139], [1226, 151]], "group_id": null, "shape_type": "rectangle", "flags": {}}, {"label": "a", "points": [[1034, 198], [1038, 202]], "group_id": null, "shape_type": "rectangle", "flags": {}}, {"label": "a", "points": [[2034, 192], [2040, 199]], "group_id": null, "shape_type": "rectangle", "flags": {}}, {"label": "a", "points": [[1255, 131], [1267, 142]], "group_id": null, "shape_type": "rectangle", "flags": {}}, {"label": "a", "points": [[1272, 132], [1280, 138]], "group_id": null, "shape_type": "rectangle", "flags": {}}, {"label": "a", "points": [[1422, 111], [1428, 118]], "group_id": null, "shape_type": "rectangle", "flags": {}}, {"label": "a", "points": [[1309, 125], [1315, 131]], "group_id": null, "shape_type": "rectangle", "flags": {}}, {"label": "a", "points": [[1572, 615], [1584, 626]], "group_id": null, "shape_type": "rectangle", "flags": {}}, {"label": "a", "points": [[1477, 107], [1483, 114]], "group_id": null, "shape_type": "rectangle", "flags": {}}, {"label": "a", "points": [[946, 429], [984, 465]], "group_id": null, "shape_type": "rectangle", "flags": {}}, {"label": "a", "points": [[738, 522], [784, 565]], "group_id": null, "shape_type": "rectangle", "flags": {}}, {"label": "a", "points": [[495, 881], [522, 904]], "group_id": null, "shape_type": "rectangle", "flags": {}}, {"label": "a", "points": [[792, 450], [830, 484]], "group_id": null, "shape_type": "rectangle", "flags": {}}, {"label": "a", "points": [[888, 497], [932, 538]], "group_id": null, "shape_type": "rectangle", "flags": {}}, {"label": "a", "points": [[408, 935], [449, 971]], "group_id": null, "shape_type": "rectangle", "flags": {}}, {"label": "a", "points": [[891, 757], [927, 790]], "group_id": null, "shape_type": "rectangle", "flags": {}}, {"label": "a", "points": [[842, 398], [872, 424]], "group_id": null, "shape_type": "rectangle", "flags": {}}, {"label": "a", "points": [[865, 799], [901, 830]], "group_id": null, "shape_type": "rectangle", "flags": {}}, {"label": "a", "points": [[234, 934], [241, 940]], "group_id": null, "shape_type": "rectangle", "flags": {}}, {"label": "a", "points": [[950, 232], [959, 241]], "group_id": null, "shape_type": "rectangle", "flags": {}}, {"label": "a", "points": [[328, 624], [340, 637]], "group_id": null, "shape_type": "rectangle", "flags": {}}, {"label": "a", "points": [[971, 223], [982, 231]], "group_id": null, "shape_type": "rectangle", "flags": {}}, {"label": "a", "points": [[809, 212], [815, 219]], "group_id": null, "shape_type": "rectangle", "flags": {}}, {"label": "a", "points": [[802, 309], [806, 313]], "group_id": null, "shape_type": "rectangle", "flags": {}}, {"label": "a", "points": [[396, 699], [400, 703]], "group_id": null, "shape_type": "rectangle", "flags": {}}, {"label": "a", "points": [[300, 813], [310, 820]], "group_id": null, "shape_type": "rectangle", "flags": {}}, {"label": "a", "points": [[707, 397], [718, 405]], "group_id": null, "shape_type": "rectangle", "flags": {}}, {"label": "a", "points": [[1440, 105], [1454, 116]], "group_id": null, "shape_type": "rectangle", "flags": {}}, {"label": "a", "points": [[1301, 124], [1313, 132]], "group_id": null, "shape_type": "rectangle", "flags": {}}, {"label": "a", "points": [[1525, 801], [1569, 842]], "group_id": null, "shape_type": "rectangle", "flags": {}}, {"label": "a", "points": [[1879, 146], [1887, 153]], "group_id": null, "shape_type": "rectangle", "flags": {}}, {"label": "a", "points": [[1085, 476], [1122, 510]], "group_id": null, "shape_type": "rectangle", "flags": {}}, {"label": "a", "points": [[1113, 246], [1158, 286]], "group_id": null, "shape_type": "rectangle", "flags": {}}, {"label": "a", "points": [[1444, 876], [1488, 917]], "group_id": null, "shape_type": "rectangle", "flags": {}}, {"label": "a", "points": [[2017, 565], [2053, 597]], "group_id": null, "shape_type": "rectangle", "flags": {}}, {"label": "a", "points": [[2051, 977], [2089, 1011]], "group_id": null, "shape_type": "rectangle", "flags": {}}, {"label": "a", "points": [[1784, 983], [1825, 1021]], "group_id": null, "shape_type": "rectangle", "flags": {}}, {"label": "a", "points": [[1376, 113], [1388, 124]], "group_id": null, "shape_type": "rectangle", "flags": {}}, {"label": "a", "points": [[1829, 593], [1872, 632]], "group_id": null, "shape_type": "rectangle", "flags": {}}, {"label": "a", "points": [[2051, 444], [2087, 478]], "group_id": null, "shape_type": "rectangle", "flags": {}}, {"label": "a", "points": [[1998, 444], [2038, 483]], "group_id": null, "shape_type": "rectangle", "flags": {}}, {"label": "a", "points": [[1511, 623], [1548, 656]], "group_id": null, "shape_type": "rectangle", "flags": {}}, {"label": "a", "points": [[1127, 716], [1169, 754]], "group_id": null, "shape_type": "rectangle", "flags": {}}, {"label": "a", "points": [[1234, 594], [1272, 627]], "group_id": null, "shape_type": "rectangle", "flags": {}}, {"label": "a", "points": [[1145, 662], [1187, 699]], "group_id": null, "shape_type": "rectangle", "flags": {}}, {"label": "a", "points": [[1136, 867], [1160, 888]], "group_id": null, "shape_type": "rectangle", "flags": {}}, {"label": "a", "points": [[1381, 158], [1439, 215]], "group_id": null, "shape_type": "rectangle", "flags": {}}, {"label": "a", "points": [[1627, 704], [1658, 732]], "group_id": null, "shape_type": "rectangle", "flags": {}}, {"label": "a", "points": [[1906, 380], [1944, 415]], "group_id": null, "shape_type": "rectangle", "flags": {}}, {"label": "a", "points": [[1765, 215], [1806, 252]], "group_id": null, "shape_type": "rectangle", "flags": {}}, {"label": "a", "points": [[1357, 269], [1392, 302]], "group_id": null, "shape_type": "rectangle", "flags": {}}, {"label": "a", "points": [[1380, 423], [1419, 458]], "group_id": null, "shape_type": "rectangle", "flags": {}}, {"label": "a", "points": [[1564, 368], [1608, 409]], "group_id": null, "shape_type": "rectangle", "flags": {}}, {"label": "a", "points": [[1322, 829], [1342, 847]], "group_id": null, "shape_type": "rectangle", "flags": {}}, {"label": "a", "points": [[1396, 111], [1400, 118]], "group_id": null, "shape_type": "rectangle", "flags": {}}, {"label": "a", "points": [[1284, 126], [1299, 137]], "group_id": null, "shape_type": "rectangle", "flags": {}}, {"label": "a", "points": [[1856, 140], [1864, 148]], "group_id": null, "shape_type": "rectangle", "flags": {}}, {"label": "a", "points": [[1516, 107], [1520, 111]], "group_id": null, "shape_type": "rectangle", "flags": {}}, {"label": "a", "points": [[1871, 142], [1877, 147]], "group_id": null, "shape_type": "rectangle", "flags": {}}, {"label": "a", "points": [[1194, 148], [1200, 155]], "group_id": null, "shape_type": "rectangle", "flags": {}}, {"label": "a", "points": [[331, 1190], [373, 1228]], "group_id": null, "shape_type": "rectangle", "flags": {}}, {"label": "a", "points": [[765, 1551], [798, 1580]], "group_id": null, "shape_type": "rectangle", "flags": {}}, {"label": "a", "points": [[2367, 2228], [2417, 2274]], "group_id": null, "shape_type": "rectangle", "flags": {}}, {"label": "a", "points": [[1155, 2095], [1199, 2137]], "group_id": null, "shape_type": "rectangle", "flags": {}}, {"label": "a", "points": [[1843, 2655], [1872, 2681]], "group_id": null, "shape_type": "rectangle", "flags": {}}, {"label": "a", "points": [[1996, 2641], [2030, 2672]], "group_id": null, "shape_type": "rectangle", "flags": {}}, {"label": "a", "points": [[2049, 2650], [2073, 2670]], "group_id": null, "shape_type": "rectangle", "flags": {}}, {"label": "a", "points": [[1421, 2261], [1452, 2289]], "group_id": null, "shape_type": "rectangle", "flags": {}}, {"label": "a", "points": [[1237, 2381], [1276, 2417]], "group_id": null, "shape_type": "rectangle", "flags": {}}, {"label": "a", "points": [[1111, 2531], [1148, 2564]], "group_id": null, "shape_type": "rectangle", "flags": {}}, {"label": "a", "points": [[1686, 2400], [1747, 2456]], "group_id": null, "shape_type": "rectangle", "flags": {}}, {"label": "a", "points": [[1186, 2203], [1207, 2222]], "group_id": null, "shape_type": "rectangle", "flags": {}}, {"label": "a", "points": [[1214, 2190], [1244, 2217]], "group_id": null, "shape_type": "rectangle", "flags": {}}, {"label": "a", "points": [[1128, 2639], [1200, 2700]], "group_id": null, "shape_type": "rectangle", "flags": {}}, {"label": "a", "points": [[1200, 2727], [1236, 2759]], "group_id": null, "shape_type": "rectangle", "flags": {}}, {"label": "a", "points": [[1095, 2853], [1115, 2869]], "group_id": null, "shape_type": "rectangle", "flags": {}}, {"label": "a", "points": [[2018, 2818], [2099, 2877]], "group_id": null, "shape_type": "rectangle", "flags": {}}, {"label": "a", "points": [[1112, 2642], [1132, 2662]], "group_id": null, "shape_type": "rectangle", "flags": {}}, {"label": "a", "points": [[1261, 2902], [1294, 2930]], "group_id": null, "shape_type": "rectangle", "flags": {}}, {"label": "a", "points": [[452, 1687], [489, 1722]], "group_id": null, "shape_type": "rectangle", "flags": {}}, {"label": "a", "points": [[1475, 2882], [1523, 2927]], "group_id": null, "shape_type": "rectangle", "flags": {}}, {"label": "a", "points": [[1088, 2069], [1122, 2101]], "group_id": null, "shape_type": "rectangle", "flags": {}}, {"label": "a", "points": [[1369, 2232], [1398, 2259]], "group_id": null, "shape_type": "rectangle", "flags": {}}, {"label": "a", "points": [[1370, 2090], [1408, 2124]], "group_id": null, "shape_type": "rectangle", "flags": {}}, {"label": "a", "points": [[1827, 2298], [1848, 2317]], "group_id": null, "shape_type": "rectangle", "flags": {}}, {"label": "a", "points": [[1716, 2479], [1748, 2509]], "group_id": null, "shape_type": "rectangle", "flags": {}}, {"label": "a", "points": [[1214, 2754], [1239, 2775]], "group_id": null, "shape_type": "rectangle", "flags": {}}, {"label": "a", "points": [[2034, 2567], [2044, 2576]], "group_id": null, "shape_type": "rectangle", "flags": {}}, {"label": "a", "points": [[1963, 2927], [1968, 2932]], "group_id": null, "shape_type": "rectangle", "flags": {}}, {"label": "a", "points": [[1222, 2547], [1232, 2556]], "group_id": null, "shape_type": "rectangle", "flags": {}}, {"label": "a", "points": [[896, 2266], [926, 2294]], "group_id": null, "shape_type": "rectangle", "flags": {}}, {"label": "a", "points": [[960, 2218], [991, 2246]], "group_id": null, "shape_type": "rectangle", "flags": {}}, {"label": "a", "points": [[992, 2297], [1029, 2332]], "group_id": null, "shape_type": "rectangle", "flags": {}}, {"label": "a", "points": [[463, 2216], [539, 2297]], "group_id": null, "shape_type": "rectangle", "flags": {}}, {"label": "a", "points": [[1916, 2501], [1955, 2537]], "group_id": null, "shape_type": "rectangle", "flags": {}}, {"label": "a", "points": [[1564, 2479], [1608, 2519]], "group_id": null, "shape_type": "rectangle", "flags": {}}, {"label": "a", "points": [[1828, 2591], [1869, 2628]], "group_id": null, "shape_type": "rectangle", "flags": {}}, {"label": "a", "points": [[1494, 2112], [1526, 2141]], "group_id": null, "shape_type": "rectangle", "flags": {}}, {"label": "a", "points": [[2196, 2102], [2241, 2144]], "group_id": null, "shape_type": "rectangle", "flags": {}}, {"label": "a", "points": [[2302, 2084], [2331, 2110]], "group_id": null, "shape_type": "rectangle", "flags": {}}, {"label": "a", "points": [[2596, 2526], [2603, 2532]], "group_id": null, "shape_type": "rectangle", "flags": {}}, {"label": "a", "points": [[2383, 2715], [2391, 2721]], "group_id": null, "shape_type": "rectangle", "flags": {}}, {"label": "a", "points": [[2804, 2237], [2809, 2241]], "group_id": null, "shape_type": "rectangle", "flags": {}}, {"label": "a", "points": [[2186, 2958], [2194, 2965]], "group_id": null, "shape_type": "rectangle", "flags": {}}, {"label": "a", "points": [[2702, 2399], [2708, 2404]], "group_id": null, "shape_type": "rectangle", "flags": {}}, {"label": "a", "points": [[2542, 2582], [2547, 2588]], "group_id": null, "shape_type": "rectangle", "flags": {}}, {"label": "a", "points": [[2583, 2546], [2587, 2549]], "group_id": null, "shape_type": "rectangle", "flags": {}}, {"label": "a", "points": [[2629, 2495], [2633, 2499]], "group_id": null, "shape_type": "rectangle", "flags": {}}, {"label": "a", "points": [[2738, 2348], [2744, 2352]], "group_id": null, "shape_type": "rectangle", "flags": {}}, {"label": "a", "points": [[2683, 2443], [2687, 2447]], "group_id": null, "shape_type": "rectangle", "flags": {}}, {"label": "a", "points": [[2743, 2330], [2750, 2346]], "group_id": null, "shape_type": "rectangle", "flags": {}}, {"label": "a", "points": [[2694, 2420], [2697, 2423]], "group_id": null, "shape_type": "rectangle", "flags": {}}, {"label": "a", "points": [[2767, 2302], [2774, 2308]], "group_id": null, "shape_type": "rectangle", "flags": {}}, {"label": "a", "points": [[2678, 2431], [2684, 2436]], "group_id": null, "shape_type": "rectangle", "flags": {}}, {"label": "a", "points": [[2825, 2192], [2832, 2199]], "group_id": null, "shape_type": "rectangle", "flags": {}}, {"label": "a", "points": [[2776, 2290], [2784, 2297]], "group_id": null, "shape_type": "rectangle", "flags": {}}, {"label": "a", "points": [[2250, 2808], [2257, 2823]], "group_id": null, "shape_type": "rectangle", "flags": {}}, {"label": "a", "points": [[2815, 2227], [2819, 2231]], "group_id": null, "shape_type": "rectangle", "flags": {}}, {"label": "a", "points": [[2535, 2591], [2541, 2595]], "group_id": null, "shape_type": "rectangle", "flags": {}}, {"label": "a", "points": [[1025, 2776], [1062, 2810]], "group_id": null, "shape_type": "rectangle", "flags": {}}, {"label": "a", "points": [[1084, 2216], [1111, 2241]], "group_id": null, "shape_type": "rectangle", "flags": {}}, {"label": "a", "points": [[1072, 2707], [1110, 2743]], "group_id": null, "shape_type": "rectangle", "flags": {}}, {"label": "a", "points": [[1306, 2107], [1343, 2142]], "group_id": null, "shape_type": "rectangle", "flags": {}}, {"label": "a", "points": [[1070, 2305], [1094, 2327]], "group_id": null, "shape_type": "rectangle", "flags": {}}, {"label": "a", "points": [[1375, 2830], [1410, 2862]], "group_id": null, "shape_type": "rectangle", "flags": {}}, {"label": "a", "points": [[1375, 2429], [1410, 2460]], "group_id": null, "shape_type": "rectangle", "flags": {}}, {"label": "a", "points": [[1285, 2263], [1314, 2291]], "group_id": null, "shape_type": "rectangle", "flags": {}}, {"label": "a", "points": [[963, 2542], [995, 2572]], "group_id": null, "shape_type": "rectangle", "flags": {}}, {"label": "a", "points": [[987, 2441], [1027, 2479]], "group_id": null, "shape_type": "rectangle", "flags": {}}, {"label": "a", "points": [[982, 2272], [1000, 2287]], "group_id": null, "shape_type": "rectangle", "flags": {}}, {"label": "a", "points": [[2816, 1200], [2855, 1236]], "group_id": null, "shape_type": "rectangle", "flags": {}}, {"label": "a", "points": [[2169, 1901], [2201, 1930]], "group_id": null, "shape_type": "rectangle", "flags": {}}, {"label": "a", "points": [[2603, 1807], [2648, 1848]], "group_id": null, "shape_type": "rectangle", "flags": {}}, {"label": "a", "points": [[2300, 1616], [2334, 1647]], "group_id": null, "shape_type": "rectangle", "flags": {}}, {"label": "a", "points": [[2931, 1470], [2940, 1487]], "group_id": null, "shape_type": "rectangle", "flags": {}}, {"label": "a", "points": [[2629, 1767], [2635, 1773]], "group_id": null, "shape_type": "rectangle", "flags": {}}, {"label": "a", "points": [[2900, 2031], [2906, 2038]], "group_id": null, "shape_type": "rectangle", "flags": {}}, {"label": "a", "points": [[2310, 1354], [2324, 1366]], "group_id": null, "shape_type": "rectangle", "flags": {}}, {"label": "a", "points": [[1965, 1459], [1993, 1485]], "group_id": null, "shape_type": "rectangle", "flags": {}}, {"label": "a", "points": [[1819, 1741], [1849, 1768]], "group_id": null, "shape_type": "rectangle", "flags": {}}, {"label": "a", "points": [[2022, 1196], [2057, 1228]], "group_id": null, "shape_type": "rectangle", "flags": {}}, {"label": "a", "points": [[1221, 1968], [1253, 1997]], "group_id": null, "shape_type": "rectangle", "flags": {}}, {"label": "a", "points": [[1782, 1173], [1822, 1209]], "group_id": null, "shape_type": "rectangle", "flags": {}}, {"label": "a", "points": [[1927, 1621], [1965, 1656]], "group_id": null, "shape_type": "rectangle", "flags": {}}, {"label": "a", "points": [[1173, 1424], [1213, 1460]], "group_id": null, "shape_type": "rectangle", "flags": {}}, {"label": "a", "points": [[1167, 1861], [1209, 1899]], "group_id": null, "shape_type": "rectangle", "flags": {}}, {"label": "a", "points": [[1892, 1819], [1932, 1856]], "group_id": null, "shape_type": "rectangle", "flags": {}}, {"label": "a", "points": [[1989, 1169], [2012, 1189]], "group_id": null, "shape_type": "rectangle", "flags": {}}, {"label": "a", "points": [[1995, 1247], [2048, 1299]], "group_id": null, "shape_type": "rectangle", "flags": {}}, {"label": "a", "points": [[1316, 1169], [1334, 1184]], "group_id": null, "shape_type": "rectangle", "flags": {}}, {"label": "a", "points": [[1662, 1622], [1708, 1666]], "group_id": null, "shape_type": "rectangle", "flags": {}}, {"label": "a", "points": [[1822, 1955], [1858, 1988]], "group_id": null, "shape_type": "rectangle", "flags": {}}, {"label": "a", "points": [[1556, 1272], [1594, 1307]], "group_id": null, "shape_type": "rectangle", "flags": {}}, {"label": "a", "points": [[1357, 1744], [1397, 1781]], "group_id": null, "shape_type": "rectangle", "flags": {}}, {"label": "a", "points": [[1362, 1413], [1381, 1430]], "group_id": null, "shape_type": "rectangle", "flags": {}}, {"label": "a", "points": [[1119, 2026], [1149, 2053]], "group_id": null, "shape_type": "rectangle", "flags": {}}, {"label": "a", "points": [[1076, 1284], [1140, 1352]], "group_id": null, "shape_type": "rectangle", "flags": {}}, {"label": "a", "points": [[1705, 1997], [1741, 2029]], "group_id": null, "shape_type": "rectangle", "flags": {}}, {"label": "a", "points": [[1683, 2034], [1693, 2043]], "group_id": null, "shape_type": "rectangle", "flags": {}}, {"label": "a", "points": [[1210, 1855], [1224, 1861]], "group_id": null, "shape_type": "rectangle", "flags": {}}, {"label": "a", "points": [[2627, 1051], [2669, 1090]], "group_id": null, "shape_type": "rectangle", "flags": {}}, {"label": "a", "points": [[2337, 1641], [2374, 1675]], "group_id": null, "shape_type": "rectangle", "flags": {}}, {"label": "a", "points": [[675, 2573], [699, 2595]], "group_id": null, "shape_type": "rectangle", "flags": {}}, {"label": "a", "points": [[2220, 1444], [2287, 1524]], "group_id": null, "shape_type": "rectangle", "flags": {}}, {"label": "a", "points": [[562, 2608], [574, 2619]], "group_id": null, "shape_type": "rectangle", "flags": {}}, {"label": "a", "points": [[734, 2744], [745, 2750]], "group_id": null, "shape_type": "rectangle", "flags": {}}, {"label": "a", "points": [[280, 2245], [289, 2255]], "group_id": null, "shape_type": "rectangle", "flags": {}}, {"label": "a", "points": [[711, 2727], [716, 2732]], "group_id": null, "shape_type": "rectangle", "flags": {}}, {"label": "a", "points": [[790, 2786], [795, 2791]], "group_id": null, "shape_type": "rectangle", "flags": {}}, {"label": "a", "points": [[699, 2719], [710, 2728]], "group_id": null, "shape_type": "rectangle", "flags": {}}, {"label": "a", "points": [[320, 2314], [327, 2321]], "group_id": null, "shape_type": "rectangle", "flags": {}}, {"label": "a", "points": [[547, 2596], [553, 2601]], "group_id": null, "shape_type": "rectangle", "flags": {}}, {"label": "a", "points": [[411, 2443], [416, 2447]], "group_id": null, "shape_type": "rectangle", "flags": {}}, {"label": "a", "points": [[454, 2508], [462, 2516]], "group_id": null, "shape_type": "rectangle", "flags": {}}, {"label": "a", "points": [[335, 2336], [339, 2341]], "group_id": null, "shape_type": "rectangle", "flags": {}}, {"label": "a", "points": [[269, 2224], [274, 2229]], "group_id": null, "shape_type": "rectangle", "flags": {}}, {"label": "a", "points": [[479, 2527], [488, 2535]], "group_id": null, "shape_type": "rectangle", "flags": {}}, {"label": "a", "points": [[366, 2385], [377, 2395]], "group_id": null, "shape_type": "rectangle", "flags": {}}, {"label": "a", "points": [[575, 2620], [582, 2625]], "group_id": null, "shape_type": "rectangle", "flags": {}}, {"label": "a", "points": [[2071, 1855], [2109, 1890]], "group_id": null, "shape_type": "rectangle", "flags": {}}, {"label": "a", "points": [[2311, 1304], [2348, 1338]], "group_id": null, "shape_type": "rectangle", "flags": {}}, {"label": "a", "points": [[2452, 1910], [2499, 1954]], "group_id": null, "shape_type": "rectangle", "flags": {}}, {"label": "a", "points": [[2289, 1187], [2329, 1223]], "group_id": null, "shape_type": "rectangle", "flags": {}}, {"label": "a", "points": [[2333, 1507], [2365, 1536]], "group_id": null, "shape_type": "rectangle", "flags": {}}, {"label": "a", "points": [[2127, 1702], [2183, 1754]], "group_id": null, "shape_type": "rectangle", "flags": {}}, {"label": "a", "points": [[2373, 1848], [2409, 1881]], "group_id": null, "shape_type": "rectangle", "flags": {}}, {"label": "a", "points": [[2233, 1895], [2272, 1932]], "group_id": null, "shape_type": "rectangle", "flags": {}}, {"label": "a", "points": [[2873, 1899], [2908, 1935]], "group_id": null, "shape_type": "rectangle", "flags": {}}, {"label": "a", "points": [[2801, 1065], [2833, 1095]], "group_id": null, "shape_type": "rectangle", "flags": {}}, {"label": "a", "points": [[2861, 1433], [2901, 1473]], "group_id": null, "shape_type": "rectangle", "flags": {}}, {"label": "a", "points": [[2284, 1490], [2314, 1519]], "group_id": null, "shape_type": "rectangle", "flags": {}}, {"label": "a", "points": [[2866, 1212], [2896, 1242]], "group_id": null, "shape_type": "rectangle", "flags": {}}, {"label": "a", "points": [[2902, 1777], [2925, 1799]], "group_id": null, "shape_type": "rectangle", "flags": {}}, {"label": "a", "points": [[557, 492], [563, 499]], "group_id": null, "shape_type": "rectangle", "flags": {}}], "imagePath": "04-03-2024_10-42-56.jpg", "imageData": null, "imageHeight": 3120, "imageWidth": 3120}